Workbook

Sheet 📊 Dashboard
B2: EMPRESA MANUFATUREIRA — CONTROLO FINANCEIRO DE ENCOMENDAS
B3: Painel de Gestão | Encomendas · Fornecedores · Fluxo de Caixa
B6: RESUMO EXECUTIVO — POSIÇÃO ACTUAL
B7: Total Encomendas Em Aberto | C7: Receita Prevista (€) | D7: Total a Pagar Fornecedores (€) | E7: Saldo Pago Antecipado (€) | F7: Saldo Devedor Restante (€)
B8: =COUNTIF(Encomendas!C:C,"Em Aberto") | C8: =SUMIF(Encomendas!C:C,"Em Aberto",Encomendas!F:F) | D8: =SUMIF(Encomendas!C:C,"Em Aberto",Encomendas!H:H) | E8: =SUMIF(Encomendas!C:C,"Em Aberto",Encomendas!I:I) | F8: =SUMIF(Encomendas!C:C,"Em Aberto",Encomendas!J:J)
B11: ENCOMENDAS EM ABERTO — VISÃO GERAL
B12: Encomenda | C12: Cliente | D12: Estado | E12: Prazo Entrega | F12: Receita (€) | G12: A Pagar Forn. (€)
B13: =IFERROR(INDEX(Encomendas!B:B,MATCH(SMALL(IF(Encomendas!C$3:C$102="Em Aberto",ROW(Encomendas!C$3:C$102)),ROW()-12),ROW(Encomendas!C$3:C$102),0)),"") | C13: =IFERROR(INDEX(Encomendas!D:D,MATCH(SMALL(IF(Encomendas!C$3:C$102="Em Aberto",ROW(Encomendas!C$3:C$102)),ROW()-12),ROW(Encomendas!C$3:C$102),0)),"") | D13: =IFERROR(INDEX(Encomendas!C:C,MATCH(SMALL(IF(Encomendas!C$3:C$102="Em Aberto",ROW(Encomendas!C$3:C$102)),ROW()-12),ROW(Encomendas!C$3:C$102),0)),"") | E13: =IFERROR(INDEX(Encomendas!G:G,MATCH(SMALL(IF(Encomendas!C$3:C$102="Em Aberto",ROW(Encomendas!C$3:C$102)),ROW()-12),ROW(Encomendas!C$3:C$102),0)),"") | F13: =IFERROR(INDEX(Encomendas!F:F,MATCH(SMALL(IF(Encomendas!C$3:C$102="Em Aberto",ROW(Encomendas!C$3:C$102)),ROW()-12),ROW(Encomendas!C$3:C$102),0)),"") | G13: =IFERROR(INDEX(Encomendas!J:J,MATCH(SMALL(IF(Encomendas!C$3:C$102="Em Aberto",ROW(Encomendas!C$3:C$102)),ROW()-12),ROW(Encomendas!C$3:C$102),0)),"")
B14: =IFERROR(INDEX(Encomendas!B:B,MATCH(SMALL(IF(Encomendas!C$3:C$102="Em Aberto",ROW(Encomendas!C$3:C$102)),ROW()-12),ROW(Encomendas!C$3:C$102),0)),"") | C14: =IFERROR(INDEX(Encomendas!D:D,MATCH(SMALL(IF(Encomendas!C$3:C$102="Em Aberto",ROW(Encomendas!C$3:C$102)),ROW()-12),ROW(Encomendas!C$3:C$102),0)),"") | D14: =IFERROR(INDEX(Encomendas!C:C,MATCH(SMALL(IF(Encomendas!C$3:C$102="Em Aberto",ROW(Encomendas!C$3:C$102)),ROW()-12),ROW(Encomendas!C$3:C$102),0)),"") | E14: =IFERROR(INDEX(Encomendas!G:G,MATCH(SMALL(IF(Encomendas!C$3:C$102="Em Aberto",ROW(Encomendas!C$3:C$102)),ROW()-12),ROW(Encomendas!C$3:C$102),0)),"") | F14: =IFERROR(INDEX(Encomendas!F:F,MATCH(SMALL(IF(Encomendas!C$3:C$102="Em Aberto",ROW(Encomendas!C$3:C$102)),ROW()-12),ROW(Encomendas!C$3:C$102),0)),"") | G14: =IFERROR(INDEX(Encomendas!J:J,MATCH(SMALL(IF(Encomendas!C$3:C$102="Em Aberto",ROW(Encomendas!C$3:C$102)),ROW()-12),ROW(Encomendas!C$3:C$102),0)),"")
B15: =IFERROR(INDEX(Encomendas!B:B,MATCH(SMALL(IF(Encomendas!C$3:C$102="Em Aberto",ROW(Encomendas!C$3:C$102)),ROW()-12),ROW(Encomendas!C$3:C$102),0)),"") | C15: =IFERROR(INDEX(Encomendas!D:D,MATCH(SMALL(IF(Encomendas!C$3:C$102="Em Aberto",ROW(Encomendas!C$3:C$102)),ROW()-12),ROW(Encomendas!C$3:C$102),0)),"") | D15: =IFERROR(INDEX(Encomendas!C:C,MATCH(SMALL(IF(Encomendas!C$3:C$102="Em Aberto",ROW(Encomendas!C$3:C$102)),ROW()-12),ROW(Encomendas!C$3:C$102),0)),"") | E15: =IFERROR(INDEX(Encomendas!G:G,MATCH(SMALL(IF(Encomendas!C$3:C$102="Em Aberto",ROW(Encomendas!C$3:C$102)),ROW()-12),ROW(Encomendas!C$3:C$102),0)),"") | F15: =IFERROR(INDEX(Encomendas!F:F,MATCH(SMALL(IF(Encomendas!C$3:C$102="Em Aberto",ROW(Encomendas!C$3:C$102)),ROW()-12),ROW(Encomendas!C$3:C$102),0)),"") | G15: =IFERROR(INDEX(Encomendas!J:J,MATCH(SMALL(IF(Encomendas!C$3:C$102="Em Aberto",ROW(Encomendas!C$3:C$102)),ROW()-12),ROW(Encomendas!C$3:C$102),0)),"")
B16: =IFERROR(INDEX(Encomendas!B:B,MATCH(SMALL(IF(Encomendas!C$3:C$102="Em Aberto",ROW(Encomendas!C$3:C$102)),ROW()-12),ROW(Encomendas!C$3:C$102),0)),"") | C16: =IFERROR(INDEX(Encomendas!D:D,MATCH(SMALL(IF(Encomendas!C$3:C$102="Em Aberto",ROW(Encomendas!C$3:C$102)),ROW()-12),ROW(Encomendas!C$3:C$102),0)),"") | D16: =IFERROR(INDEX(Encomendas!C:C,MATCH(SMALL(IF(Encomendas!C$3:C$102="Em Aberto",ROW(Encomendas!C$3:C$102)),ROW()-12),ROW(Encomendas!C$3:C$102),0)),"") | E16: =IFERROR(INDEX(Encomendas!G:G,MATCH(SMALL(IF(Encomendas!C$3:C$102="Em Aberto",ROW(Encomendas!C$3:C$102)),ROW()-12),ROW(Encomendas!C$3:C$102),0)),"") | F16: =IFERROR(INDEX(Encomendas!F:F,MATCH(SMALL(IF(Encomendas!C$3:C$102="Em Aberto",ROW(Encomendas!C$3:C$102)),ROW()-12),ROW(Encomendas!C$3:C$102),0)),"") | G16: =IFERROR(INDEX(Encomendas!J:J,MATCH(SMALL(IF(Encomendas!C$3:C$102="Em Aberto",ROW(Encomendas!C$3:C$102)),ROW()-12),ROW(Encomendas!C$3:C$102),0)),"")
B17: =IFERROR(INDEX(Encomendas!B:B,MATCH(SMALL(IF(Encomendas!C$3:C$102="Em Aberto",ROW(Encomendas!C$3:C$102)),ROW()-12),ROW(Encomendas!C$3:C$102),0)),"") | C17: =IFERROR(INDEX(Encomendas!D:D,MATCH(SMALL(IF(Encomendas!C$3:C$102="Em Aberto",ROW(Encomendas!C$3:C$102)),ROW()-12),ROW(Encomendas!C$3:C$102),0)),"") | D17: =IFERROR(INDEX(Encomendas!C:C,MATCH(SMALL(IF(Encomendas!C$3:C$102="Em Aberto",ROW(Encomendas!C$3:C$102)),ROW()-12),ROW(Encomendas!C$3:C$102),0)),"") | E17: =IFERROR(INDEX(Encomendas!G:G,MATCH(SMALL(IF(Encomendas!C$3:C$102="Em Aberto",ROW(Encomendas!C$3:C$102)),ROW()-12),ROW(Encomendas!C$3:C$102),0)),"") | F17: =IFERROR(INDEX(Encomendas!F:F,MATCH(SMALL(IF(Encomendas!C$3:C$102="Em Aberto",ROW(Encomendas!C$3:C$102)),ROW()-12),ROW(Encomendas!C$3:C$102),0)),"") | G17: =IFERROR(INDEX(Encomendas!J:J,MATCH(SMALL(IF(Encomendas!C$3:C$102="Em Aberto",ROW(Encomendas!C$3:C$102)),ROW()-12),ROW(Encomendas!C$3:C$102),0)),"")
B18: =IFERROR(INDEX(Encomendas!B:B,MATCH(SMALL(IF(Encomendas!C$3:C$102="Em Aberto",ROW(Encomendas!C$3:C$102)),ROW()-12),ROW(Encomendas!C$3:C$102),0)),"") | C18: =IFERROR(INDEX(Encomendas!D:D,MATCH(SMALL(IF(Encomendas!C$3:C$102="Em Aberto",ROW(Encomendas!C$3:C$102)),ROW()-12),ROW(Encomendas!C$3:C$102),0)),"") | D18: =IFERROR(INDEX(Encomendas!C:C,MATCH(SMALL(IF(Encomendas!C$3:C$102="Em Aberto",ROW(Encomendas!C$3:C$102)),ROW()-12),ROW(Encomendas!C$3:C$102),0)),"") | E18: =IFERROR(INDEX(Encomendas!G:G,MATCH(SMALL(IF(Encomendas!C$3:C$102="Em Aberto",ROW(Encomendas!C$3:C$102)),ROW()-12),ROW(Encomendas!C$3:C$102),0)),"") | F18: =IFERROR(INDEX(Encomendas!F:F,MATCH(SMALL(IF(Encomendas!C$3:C$102="Em Aberto",ROW(Encomendas!C$3:C$102)),ROW()-12),ROW(Encomendas!C$3:C$102),0)),"") | G18: =IFERROR(INDEX(Encomendas!J:J,MATCH(SMALL(IF(Encomendas!C$3:C$102="Em Aberto",ROW(Encomendas!C$3:C$102)),ROW()-12),ROW(Encomendas!C$3:C$102),0)),"")
B19: =IFERROR(INDEX(Encomendas!B:B,MATCH(SMALL(IF(Encomendas!C$3:C$102="Em Aberto",ROW(Encomendas!C$3:C$102)),ROW()-12),ROW(Encomendas!C$3:C$102),0)),"") | C19: =IFERROR(INDEX(Encomendas!D:D,MATCH(SMALL(IF(Encomendas!C$3:C$102="Em Aberto",ROW(Encomendas!C$3:C$102)),ROW()-12),ROW(Encomendas!C$3:C$102),0)),"") | D19: =IFERROR(INDEX(Encomendas!C:C,MATCH(SMALL(IF(Encomendas!C$3:C$102="Em Aberto",ROW(Encomendas!C$3:C$102)),ROW()-12),ROW(Encomendas!C$3:C$102),0)),"") | E19: =IFERROR(INDEX(Encomendas!G:G,MATCH(SMALL(IF(Encomendas!C$3:C$102="Em Aberto",ROW(Encomendas!C$3:C$102)),ROW()-12),ROW(Encomendas!C$3:C$102),0)),"") | F19: =IFERROR(INDEX(Encomendas!F:F,MATCH(SMALL(IF(Encomendas!C$3:C$102="Em Aberto",ROW(Encomendas!C$3:C$102)),ROW()-12),ROW(Encomendas!C$3:C$102),0)),"") | G19: =IFERROR(INDEX(Encomendas!J:J,MATCH(SMALL(IF(Encomendas!C$3:C$102="Em Aberto",ROW(Encomendas!C$3:C$102)),ROW()-12),ROW(Encomendas!C$3:C$102),0)),"")
B20: =IFERROR(INDEX(Encomendas!B:B,MATCH(SMALL(IF(Encomendas!C$3:C$102="Em Aberto",ROW(Encomendas!C$3:C$102)),ROW()-12),ROW(Encomendas!C$3:C$102),0)),"") | C20: =IFERROR(INDEX(Encomendas!D:D,MATCH(SMALL(IF(Encomendas!C$3:C$102="Em Aberto",ROW(Encomendas!C$3:C$102)),ROW()-12),ROW(Encomendas!C$3:C$102),0)),"") | D20: =IFERROR(INDEX(Encomendas!C:C,MATCH(SMALL(IF(Encomendas!C$3:C$102="Em Aberto",ROW(Encomendas!C$3:C$102)),ROW()-12),ROW(Encomendas!C$3:C$102),0)),"") | E20: =IFERROR(INDEX(Encomendas!G:G,MATCH(SMALL(IF(Encomendas!C$3:C$102="Em Aberto",ROW(Encomendas!C$3:C$102)),ROW()-12),ROW(Encomendas!C$3:C$102),0)),"") | F20: =IFERROR(INDEX(Encomendas!F:F,MATCH(SMALL(IF(Encomendas!C$3:C$102="Em Aberto",ROW(Encomendas!C$3:C$102)),ROW()-12),ROW(Encomendas!C$3:C$102),0)),"") | G20: =IFERROR(INDEX(Encomendas!J:J,MATCH(SMALL(IF(Encomendas!C$3:C$102="Em Aberto",ROW(Encomendas!C$3:C$102)),ROW()-12),ROW(Encomendas!C$3:C$102),0)),"")
B21: =IFERROR(INDEX(Encomendas!B:B,MATCH(SMALL(IF(Encomendas!C$3:C$102="Em Aberto",ROW(Encomendas!C$3:C$102)),ROW()-12),ROW(Encomendas!C$3:C$102),0)),"") | C21: =IFERROR(INDEX(Encomendas!D:D,MATCH(SMALL(IF(Encomendas!C$3:C$102="Em Aberto",ROW(Encomendas!C$3:C$102)),ROW()-12),ROW(Encomendas!C$3:C$102),0)),"") | D21: =IFERROR(INDEX(Encomendas!C:C,MATCH(SMALL(IF(Encomendas!C$3:C$102="Em Aberto",ROW(Encomendas!C$3:C$102)),ROW()-12),ROW(Encomendas!C$3:C$102),0)),"") | E21: =IFERROR(INDEX(Encomendas!G:G,MATCH(SMALL(IF(Encomendas!C$3:C$102="Em Aberto",ROW(Encomendas!C$3:C$102)),ROW()-12),ROW(Encomendas!C$3:C$102),0)),"") | F21: =IFERROR(INDEX(Encomendas!F:F,MATCH(SMALL(IF(Encomendas!C$3:C$102="Em Aberto",ROW(Encomendas!C$3:C$102)),ROW()-12),ROW(Encomendas!C$3:C$102),0)),"") | G21: =IFERROR(INDEX(Encomendas!J:J,MATCH(SMALL(IF(Encomendas!C$3:C$102="Em Aberto",ROW(Encomendas!C$3:C$102)),ROW()-12),ROW(Encomendas!C$3:C$102),0)),"")
B22: =IFERROR(INDEX(Encomendas!B:B,MATCH(SMALL(IF(Encomendas!C$3:C$102="Em Aberto",ROW(Encomendas!C$3:C$102)),ROW()-12),ROW(Encomendas!C$3:C$102),0)),"") | C22: =IFERROR(INDEX(Encomendas!D:D,MATCH(SMALL(IF(Encomendas!C$3:C$102="Em Aberto",ROW(Encomendas!C$3:C$102)),ROW()-12),ROW(Encomendas!C$3:C$102),0)),"") | D22: =IFERROR(INDEX(Encomendas!C:C,MATCH(SMALL(IF(Encomendas!C$3:C$102="Em Aberto",ROW(Encomendas!C$3:C$102)),ROW()-12),ROW(Encomendas!C$3:C$102),0)),"") | E22: =IFERROR(INDEX(Encomendas!G:G,MATCH(SMALL(IF(Encomendas!C$3:C$102="Em Aberto",ROW(Encomendas!C$3:C$102)),ROW()-12),ROW(Encomendas!C$3:C$102),0)),"") | F22: =IFERROR(INDEX(Encomendas!F:F,MATCH(SMALL(IF(Encomendas!C$3:C$102="Em Aberto",ROW(Encomendas!C$3:C$102)),ROW()-12),ROW(Encomendas!C$3:C$102),0)),"") | G22: =IFERROR(INDEX(Encomendas!J:J,MATCH(SMALL(IF(Encomendas!C$3:C$102="Em Aberto",ROW(Encomendas!C$3:C$102)),ROW()-12),ROW(Encomendas!C$3:C$102),0)),"")
B23: =IFERROR(INDEX(Encomendas!B:B,MATCH(SMALL(IF(Encomendas!C$3:C$102="Em Aberto",ROW(Encomendas!C$3:C$102)),ROW()-12),ROW(Encomendas!C$3:C$102),0)),"") | C23: =IFERROR(INDEX(Encomendas!D:D,MATCH(SMALL(IF(Encomendas!C$3:C$102="Em Aberto",ROW(Encomendas!C$3:C$102)),ROW()-12),ROW(Encomendas!C$3:C$102),0)),"") | D23: =IFERROR(INDEX(Encomendas!C:C,MATCH(SMALL(IF(Encomendas!C$3:C$102="Em Aberto",ROW(Encomendas!C$3:C$102)),ROW()-12),ROW(Encomendas!C$3:C$102),0)),"") | E23: =IFERROR(INDEX(Encomendas!G:G,MATCH(SMALL(IF(Encomendas!C$3:C$102="Em Aberto",ROW(Encomendas!C$3:C$102)),ROW()-12),ROW(Encomendas!C$3:C$102),0)),"") | F23: =IFERROR(INDEX(Encomendas!F:F,MATCH(SMALL(IF(Encomendas!C$3:C$102="Em Aberto",ROW(Encomendas!C$3:C$102)),ROW()-12),ROW(Encomendas!C$3:C$102),0)),"") | G23: =IFERROR(INDEX(Encomendas!J:J,MATCH(SMALL(IF(Encomendas!C$3:C$102="Em Aberto",ROW(Encomendas!C$3:C$102)),ROW()-12),ROW(Encomendas!C$3:C$102),0)),"")
B24: =IFERROR(INDEX(Encomendas!B:B,MATCH(SMALL(IF(Encomendas!C$3:C$102="Em Aberto",ROW(Encomendas!C$3:C$102)),ROW()-12),ROW(Encomendas!C$3:C$102),0)),"") | C24: =IFERROR(INDEX(Encomendas!D:D,MATCH(SMALL(IF(Encomendas!C$3:C$102="Em Aberto",ROW(Encomendas!C$3:C$102)),ROW()-12),ROW(Encomendas!C$3:C$102),0)),"") | D24: =IFERROR(INDEX(Encomendas!C:C,MATCH(SMALL(IF(Encomendas!C$3:C$102="Em Aberto",ROW(Encomendas!C$3:C$102)),ROW()-12),ROW(Encomendas!C$3:C$102),0)),"") | E24: =IFERROR(INDEX(Encomendas!G:G,MATCH(SMALL(IF(Encomendas!C$3:C$102="Em Aberto",ROW(Encomendas!C$3:C$102)),ROW()-12),ROW(Encomendas!C$3:C$102),0)),"") | F24: =IFERROR(INDEX(Encomendas!F:F,MATCH(SMALL(IF(Encomendas!C$3:C$102="Em Aberto",ROW(Encomendas!C$3:C$102)),ROW()-12),ROW(Encomendas!C$3:C$102),0)),"") | G24: =IFERROR(INDEX(Encomendas!J:J,MATCH(SMALL(IF(Encomendas!C$3:C$102="Em Aberto",ROW(Encomendas!C$3:C$102)),ROW()-12),ROW(Encomendas!C$3:C$102),0)),"")
... B32: =IFERROR(INDEX(Encomendas!B:B,MATCH(SMALL(IF(Encomendas!C$3:C$102="Em Aberto",ROW(Encomendas!C$3:C$102)),ROW()-12),ROW(Encomendas!C$3:C$102),0)),"") | C32: =IFERROR(INDEX(Encomendas!D:D,MATCH(SMALL(IF(Encomendas!C$3:C$102="Em Aberto",ROW(Encomendas!C$3:C$102)),ROW()-12),ROW(Encomendas!C$3:C$102),0)),"") | D32: =IFERROR(INDEX(Encomendas!C:C,MATCH(SMALL(IF(Encomendas!C$3:C$102="Em Aberto",ROW(Encomendas!C$3:C$102)),ROW()-12),ROW(Encomendas!C$3:C$102),0)),"") | E32: =IFERROR(INDEX(Encomendas!G:G,MATCH(SMALL(IF(Encomendas!C$3:C$102="Em Aberto",ROW(Encomendas!C$3:C$102)),ROW()-12),ROW(Encomendas!C$3:C$102),0)),"") | F32: =IFERROR(INDEX(Encomendas!F:F,MATCH(SMALL(IF(Encomendas!C$3:C$102="Em Aberto",ROW(Encomendas!C$3:C$102)),ROW()-12),ROW(Encomendas!C$3:C$102),0)),"") | G32: =IFERROR(INDEX(Encomendas!J:J,MATCH(SMALL(IF(Encomendas!C$3:C$102="Em Aberto",ROW(Encomendas!C$3:C$102)),ROW()-12),ROW(Encomendas!C$3:C$102),0)),"")
B34: Actualizado automaticamente a partir das abas Encomendas e Fornecedores | Não editar este painel directamente

Sheet Encomendas
A1: EMPRESA MANUFATUREIRA — REGISTO DE ENCOMENDAS
A2: Nº | B2: ID Encomenda | C2: Estado | D2: Cliente | E2: Produto / Descrição | F2: Receita Cliente (€) | G2: Prazo Entrega | H2: Total Custo Forn. (€) | I2: Pago Antecip. (€) | J2: Saldo Devedor (€) | K2: Margem Bruta (€) | L2: Margem (%) | M2: Observações
A3: 1 | B3: ENC-2026-001 | C3: Em Aberto | D3: Cliente A | E3: Sofá 3L ref. SL220 (x10) | F3: 12500 | G3: 46127 | H3: 8200 | I3: 3280 | J3: =H3-I3 | K3: =F3-H3 | L3: =IFERROR(K3/F3,0)
A4: 2 | B4: ENC-2026-002 | C4: Em Produção | D4: Cliente B | E4: Cadeiras ref. CA110 (x30) | F4: 9800 | G4: 46142 | H4: 6100 | I4: 2440 | J4: =H4-I4 | K4: =F4-H4 | L4: =IFERROR(K4/F4,0)
A5: 3 | B5: ENC-2026-003 | C5: Confirmada | D5: Cliente C | E5: Cabeceiras ref. CB05 (x20) | F5: 4200 | G5: 46152 | H5: 2800 | I5: 1120 | J5: =H5-I5 | K5: =F5-H5 | L5: =IFERROR(K5/F5,0)
A6: =IFERROR(ROW()-2,"") | J6: =IFERROR(H6-I6,"") | K6: =IFERROR(F6-H6,"") | L6: =IFERROR(K6/F6,"")
A7: =IFERROR(ROW()-2,"") | J7: =IFERROR(H7-I7,"") | K7: =IFERROR(F7-H7,"") | L7: =IFERROR(K7/F7,"")
A8: =IFERROR(ROW()-2,"") | J8: =IFERROR(H8-I8,"") | K8: =IFERROR(F8-H8,"") | L8: =IFERROR(K8/F8,"")
A9: =IFERROR(ROW()-2,"") | J9: =IFERROR(H9-I9,"") | K9: =IFERROR(F9-H9,"") | L9: =IFERROR(K9/F9,"")
A10: =IFERROR(ROW()-2,"") | J10: =IFERROR(H10-I10,"") | K10: =IFERROR(F10-H10,"") | L10: =IFERROR(K10/F10,"")
A11: =IFERROR(ROW()-2,"") | J11: =IFERROR(H11-I11,"") | K11: =IFERROR(F11-H11,"") | L11: =IFERROR(K11/F11,"")
A12: =IFERROR(ROW()-2,"") | J12: =IFERROR(H12-I12,"") | K12: =IFERROR(F12-H12,"") | L12: =IFERROR(K12/F12,"")
A13: =IFERROR(ROW()-2,"") | J13: =IFERROR(H13-I13,"") | K13: =IFERROR(F13-H13,"") | L13: =IFERROR(K13/F13,"")
A14: =IFERROR(ROW()-2,"") | J14: =IFERROR(H14-I14,"") | K14: =IFERROR(F14-H14,"") | L14: =IFERROR(K14/F14,"")
A15: =IFERROR(ROW()-2,"") | J15: =IFERROR(H15-I15,"") | K15: =IFERROR(F15-H15,"") | L15: =IFERROR(K15/F15,"")
A16: =IFERROR(ROW()-2,"") | J16: =IFERROR(H16-I16,"") | K16: =IFERROR(F16-H16,"") | L16: =IFERROR(K16/F16,"")
A17: =IFERROR(ROW()-2,"") | J17: =IFERROR(H17-I17,"") | K17: =IFERROR(F17-H17,"") | L17: =IFERROR(K17/F17,"")
... A102: =IFERROR(ROW()-2,"") | J102: =IFERROR(H102-I102,"") | K102: =IFERROR(F102-H102,"") | L102: =IFERROR(K102/F102,"")

Sheet Fornecedores
A1: EMPRESA MANUFATUREIRA — FORNECEDORES POR ENCOMENDA
A2: Nº | B2: ID Encomenda | C2: Fornecedor | D2: Tipo Material | E2: Valor Total (€) | F2: Cond. Pagamento | G2: Valor Antecip. (€) | H2: Data Pagto Antecip. | I2: Valor Restante (€) | J2: Data Pagto Restante | K2: Estado Pagamento | L2: Observações
A3: 1 | B3: ENC-2026-001 | C3: Fornecedor Cascos | D3: Casco/Estrutura | E3: 4100 | F3: 50/50 | G3: 2050 | H3: 46091 | I3: =IFERROR(E3-G3,"") | K3: Antecipado Pago
A4: 2 | B4: ENC-2026-001 | C4: Fornecedor Tecidos | D4: Tecido | E4: 2800 | F4: 40/60 | G4: 1120 | H4: 46093 | I4: =IFERROR(E4-G4,"") | K4: Antecipado Pago
A5: 3 | B5: ENC-2026-001 | C5: Fornecedor Metálicos | D5: Peças Metálicas | E5: 1300 | F5: 30/70 | G5: 390 | H5: 46096 | I5: =IFERROR(E5-G5,"") | K5: Antecipado Pago
A6: 4 | B6: ENC-2026-002 | C6: Fornecedor Cascos | D6: Casco/Estrutura | E6: 3200 | F6: 50/50 | G6: 1600 | H6: 46101 | I6: =IFERROR(E6-G6,"") | K6: Antecipado Pago
A7: 5 | B7: ENC-2026-002 | C7: Fornecedor Espumas | D7: Espuma | E7: 900 | F7: 30/70 | G7: 270 | H7: 46103 | I7: =IFERROR(E7-G7,"") | K7: Antecipado Pago
A8: 6 | B8: ENC-2026-002 | C8: Fornecedor Tecidos | D8: Tecido | E8: 2000 | F8: 40/60 | G8: 800 | H8: 46106 | I8: =IFERROR(E8-G8,"") | K8: Antecipado Pago
A9: 7 | B9: ENC-2026-003 | C9: Fornecedor Metálicos | D9: Peças Metálicas | E9: 800 | F9: 50/50 | G9: 400 | H9: 46113 | I9: =IFERROR(E9-G9,"") | K9: Pendente
A10: 8 | B10: ENC-2026-003 | C10: Fornecedor Tecidos | D10: Tecido | E10: 2000 | F10: 50/50 | G10: 1000 | H10: 46113 | I10: =IFERROR(E10-G10,"") | K10: Pendente
I11: =IFERROR(E11-G11,"")
I12: =IFERROR(E12-G12,"")
I13: =IFERROR(E13-G13,"")
I14: =IFERROR(E14-G14,"")
I15: =IFERROR(E15-G15,"")
I16: =IFERROR(E16-G16,"")
I17: =IFERROR(E17-G17,"")
I18: =IFERROR(E18-G18,"")
I19: =IFERROR(E19-G19,"")
I20: =IFERROR(E20-G20,"")
I21: =IFERROR(E21-G21,"")
I22: =IFERROR(E22-G22,"")
... I202: =IFERROR(E202-G202,"")

Sheet 📅 Projecção Caixa
B1: EMPRESA MANUFATUREIRA — PROJECÇÃO DE PAGAMENTOS A FORNECEDORES
B3: Fornecedor / Encomenda | C3: Abr/2026 | D3: Mai/2026 | E3: Jun/2026 | F3: Jul/2026 | G3: Ago/2026 | H3: Set/2026
B4: ENTRADAS — RECEBIMENTOS DE CLIENTES
B5: Recebimentos previstos (clientes confirmados) | C5: 0 | D5: 0 | E5: 0 | F5: 0 | G5: 0 | H5: 0
B6: Recebimentos previstos (clientes em negociação) | C6: 0 | D6: 0 | E6: 0 | F6: 0 | G6: 0 | H6: 0
B8: SAÍDAS — PAGAMENTOS A FORNECEDORES
B9: Antecipações a fornecedores (50%) | C9: 0 | D9: 0 | E9: 0 | F9: 0 | G9: 0 | H9: 0
B10: Saldo restante a fornecedores (entrega MP) | C10: 0 | D10: 0 | E10: 0 | F10: 0 | G10: 0 | H10: 0
B11: Fornecedor: Cascos / Estruturas | C11: 0 | D11: 0 | E11: 0 | F11: 0 | G11: 0 | H11: 0
B12: Fornecedor: Tecidos | C12: 0 | D12: 0 | E12: 0 | F12: 0 | G12: 0 | H12: 0
B13: Fornecedor: Espumas | C13: 0 | D13: 0 | E13: 0 | F13: 0 | G13: 0 | H13: 0
B14: Fornecedor: Peças Metálicas | C14: 0 | D14: 0 | E14: 0 | F14: 0 | G14: 0 | H14: 0
B16: SALDO LÍQUIDO DO PERÍODO
B17: =Entradas − Saídas | C17: 0 | D17: 0 | E17: 0 | F17: 0 | G17: 0 | H17: 0
B20: Células em azul = valores a inserir manualmente | Actualizar semanalmente com o dono

Sheet ✅ Checklist BOM
B1: EMPRESA MANUFATUREIRA — CHECKLIST DE VALIDAÇÃO DA FICHA TÉCNICA (BOM)
B3: ID Encomenda:
B4: Cliente:
B5: Responsável Validação:
B6: Data Validação:
B8: ITEM DE VERIFICAÇÃO | C8: RESPONSÁVEL | D8: VERIFICADO? | E8: OBSERVAÇÃO
B9: PRÉ-LANÇAMENTO
B10: Orçamento do cliente recebido e aprovado por escrito | C10: Dono | D10: Pendente
B11: Todos os orçamentos de fornecedores recebidos (casco, tecido, metal, espuma) | C11: Dono | D11: Pendente
B12: Margem bruta calculada e aprovada (mínimo definido pela gestão) | C12: CFO | D12: Pendente
B13: Condições de pagamento acordadas com cada fornecedor registadas no sistema | C13: Dono | D13: Pendente
B14: FICHA TÉCNICA (BOM)
B15: Referência do produto correcta e existente no AS/400 | C15: Planeamento | D15: Pendente
B16: Quantidades de matéria-prima conferidas com o projecto 3D do design | C16: Planeamento | D16: Pendente
B17: Medidas do cliente incorporadas correctamente na ficha | C17: Design | D17: Pendente
B18: Tecido seleccionado corresponde ao pedido pelo cliente (ref. e cor) | C18: Design | D18: Pendente
B19: Espessura de espuma conforme especificação do modelo | C19: Produção | D19: Pendente
B20: Estrutura metálica/casco compatível com o modelo | C20: Produção | D20: Pendente
B21: Consumo de cola e acessórios estimado correctamente | C21: Planeamento | D21: Pendente
B22: ANTES DE GERAR NECESSIDADE DE COMPRA
B23: Ficha técnica revista por segundo responsável (dupla conferência) | C23: Gabriel / CFO | D23: Pendente
B24: Comparação com ficha de encomenda similar anterior (benchmarking) | C24: Gabriel | D24: Pendente
B25: Stock actual verificado — evitar compra de material já disponível | C25: Armazém | D25: Pendente
B26: Prazo de entrega do fornecedor confirmado vs. prazo dado ao cliente | C26: Planeamento | D26: Pendente
B27: Limite de crédito com fornecedor verificado (saldo devedor em aberto) | C27: Gabriel | D27: Pendente
B28: PÓS-LANÇAMENTO
B29: Necessidade de compra gerada e enviada ao responsável de compras | C29: Planeamento | D29: Pendente
B30: Pedido de compra (PO) aprovado pelo CFO antes do envio ao fornecedor | C30: CFO | D30: Pendente
B31: Data de pagamento antecipado registada na aba Fornecedores | C31: Gabriel | D31: Pendente
B32: Data prevista de recepção de matéria-prima registada no sistema | C32: Planeamento | D32: Pendente

Sheet ⚠ Ocorrências
A1: EMPRESA MANUFATUREIRA — REGISTO DE OCORRÊNCIAS E IRREGULARIDADES
A2: Nº | B2: Data | C2: ID Encomenda | D2: Área | E2: Tipo | F2: Descrição da Ocorrência | G2: Impacto (€) | H2: Acção Tomada | I2: Estado | J2: Responsável | K2: Data Resolução
A3: 1 | B3: 46037 | C3: ENC-2026-001 | D3: BOM/ERP | E3: Erro de Dados | F3: Discrepâncias entre BOM e consumo real no AS/400 — quantidades de espuma incorrectas em 18 fichas técnicas | G3: 2300 | H3: Correcção de dados mestres e validação cruzada implementada | I3: Resolvido | J3: Gabriel | K3: 46054
A4: 2 | B4: 46063 | C4: ENC-2026-002 | D4: Compras | E4: Irregularidade | F4: 3 funcionários aprovando e recebendo o mesmo pedido de compra — violação de SoD | G4: 0 | H4: Implementação de Segregação de Funções e Blind Receiving | I4: Resolvido | J4: Gabriel | K4: 46073
A5: 3 | B5: 46086 | C5: ENC-2026-001 | D5: Tesouraria | E5: Pagamento em Atraso | F5: Fornecedor Fornecedor Cascos com saldo devedor de €4.100 — bloqueio de entrega comunicado | G5: 4100 | H5: Pagamento agendado e quitado. Processo de projecção de caixa iniciado | I5: Resolvido | J5: CFO | K5: 46089
